Metadata-Version: 2.1
Name: numbers-of-unique-characters
Version: 0.6
Summary: Python module is used to find unique characters.
Home-page: https://git.foxminded.com.ua/Yuliia_Nikolaevna/foxminded/
Author: Yuliia_Kuzminska
Author-email: yuliia.nikolaevna86@gmail.com
License: UNKNOWN
Platform: UNKNOWN
Classifier: Programming Language :: Python :: 3.8
Classifier: Programming Language :: Python :: Implementation :: PyPy
Classifier: Framework :: Pytest
Classifier: License :: OSI Approved :: MIT License
Classifier: Operating System :: OS Independent
Requires-Python: >=3.8
